README.md
setup.cfg
setup.py
pybtree/__init__.py
pybtree/btree.py
pybtree/pysearch.py
pybtree.egg-info/PKG-INFO
pybtree.egg-info/SOURCES.txt
pybtree.egg-info/dependency_links.txt
pybtree.egg-info/top_level.txt