Metadata-Version: 1.0
Name: pybtree
Version: 1.0
Summary: An on-disk BTree implementation in Python 3.
Home-page: https://github.com/btrevizan/pybtree
Author: Bernardo Trevizan
Author-email: trevizanbernardo@gmail.com
License: UNKNOWN
Keywords: file,binary,search,btree,on-disk,python
Platform: UNKNOWN
